camera/__init__.py
camera/__main__.py
camera/camera_locations.py
camera/capture.py
camera/capture_functions.py
camera/cli_parser.py
camera/config.py
camera/kenya_capture.py
camera/timing_functions.py
camera_capture-1.1.0.dist-info/licenses/license.txt
camera_capture-1.1.0.dist-info/METADATA
camera_capture-1.1.0.dist-info/WHEEL
camera_capture-1.1.0.dist-info/entry_points.txt
camera_capture-1.1.0.dist-info/top_level.txt
camera_capture-1.1.0.dist-info/RECORD
