Metadata-Version: 2.4
Name: camera_capture
Version: 1.1.0
Summary: An app to capture and process webcam data.
Author-email: Willem Nieuwenhuis <w.nieuwenhuis@utwente.nl>
Project-URL: source, https://github.com/WillemNieuwenhuisSoft/camera_capture
Requires-Python: >=3.7
License-File: license.txt
Requires-Dist: requests
Requires-Dist: beautifulsoup4
Requires-Dist: pandas
Provides-Extra: test
Requires-Dist: pytest; extra == "test"
Requires-Dist: pytest-cov; extra == "test"
Requires-Dist: coverage; extra == "test"
Provides-Extra: lint
Requires-Dist: autopep8; extra == "lint"
Requires-Dist: flake8; extra == "lint"
Dynamic: license-file
